<annotation>
	<folder>HandDetectionDataset</folder>
	<filename>Buffy_275.jpg</filename>
	<size>
		<width>523</width>
		<height>641</height>
		<depth>3</depth>
	</size>
	<segmented>0</segmented>
	<object>
		<name>hand</name>
		<pose>Unspecified</pose>
		<truncated>0</truncated>
		<difficult>0</difficult>
		<bndbox>
			<xmin>430.0603297476319</xmin>
			<ymin>187.88405734600454</ymin>
			<xmax>490.9396702523681</xmax>
			<ymax>246.1159426539955</ymax>
		</bndbox>
	</object>
	<object>
		<name>hand</name>
		<pose>Unspecified</pose>
		<truncated>0</truncated>
		<difficult>0</difficult>
		<bndbox>
			<xmin>450.7218693897068</xmin>
			<ymin>246.1159426539955</ymin>
			<xmax>490.9396702523681</xmax>
			<ymax>225.8840573460045</ymax>
		</bndbox>
	</object>
</annotation>
