<annotation>
	<folder>HandDetectionDataset</folder>
	<filename>Poselet_355.jpg</filename>
	<size>
		<width>1024</width>
		<height>683</height>
		<depth>3</depth>
	</size>
	<segmented>0</segmented>
	<object>
		<name>hand</name>
		<pose>Unspecified</pose>
		<truncated>0</truncated>
		<difficult>0</difficult>
		<bndbox>
			<xmin>354.7006667474939</xmin>
			<ymin>142.03783692955068</ymin>
			<xmax>396.26011756623143</xmax>
			<ymax>179.191553751453</ymax>
		</bndbox>
	</object>
	<object>
		<name>hand</name>
		<pose>Unspecified</pose>
		<truncated>0</truncated>
		<difficult>0</difficult>
		<bndbox>
			<xmin>401.50393331881423</xmin>
			<ymin>147.5432132736367</ymin>
			<xmax>396.26011756623143</xmax>
			<ymax>147.5432132736367</ymax>
		</bndbox>
	</object>
	<object>
		<name>hand</name>
		<pose>Unspecified</pose>
		<truncated>0</truncated>
		<difficult>0</difficult>
		<bndbox>
			<xmin>404.3206682514107</xmin>
			<ymin>147.5432132736367</ymin>
			<xmax>396.26011756623143</xmax>
			<ymax>147.5432132736367</ymax>
		</bndbox>
	</object>
	<object>
		<name>hand</name>
		<pose>Unspecified</pose>
		<truncated>0</truncated>
		<difficult>0</difficult>
		<bndbox>
			<xmin>270.3317152585365</xmin>
			<ymin>147.5432132736367</ymin>
			<xmax>354.7006667474939</xmax>
			<ymax>147.5432132736367</ymax>
		</bndbox>
	</object>
	<object>
		<name>hand</name>
		<pose>Unspecified</pose>
		<truncated>0</truncated>
		<difficult>0</difficult>
		<bndbox>
			<xmin>366.2824977376834</xmin>
			<ymin>147.5432132736367</ymin>
			<xmax>391.52909812004293</xmax>
			<ymax>147.5432132736367</ymax>
		</bndbox>
	</object>
	<object>
		<name>hand</name>
		<pose>Unspecified</pose>
		<truncated>0</truncated>
		<difficult>0</difficult>
		<bndbox>
			<xmin>394.504944108387</xmin>
			<ymin>147.5432132736367</ymin>
			<xmax>396.26011756623143</xmax>
			<ymax>147.5432132736367</ymax>
		</bndbox>
	</object>
	<object>
		<name>hand</name>
		<pose>Unspecified</pose>
		<truncated>0</truncated>
		<difficult>0</difficult>
		<bndbox>
			<xmin>396.26011756623143</xmin>
			<ymin>173.68617740736698</ymin>
			<xmax>249.57206663569954</xmax>
			<ymax>147.5432132736367</ymax>
		</bndbox>
	</object>
	<object>
		<name>hand</name>
		<pose>Unspecified</pose>
		<truncated>0</truncated>
		<difficult>0</difficult>
		<bndbox>
			<xmin>396.26011756623143</xmin>
			<ymin>173.68617740736698</ymin>
			<xmax>354.7006667474939</xmax>
			<ymax>549.8008721644046</ymax>
		</bndbox>
	</object>
	<object>
		<name>hand</name>
		<pose>Unspecified</pose>
		<truncated>0</truncated>
		<difficult>0</difficult>
		<bndbox>
			<xmin>354.7006667474939</xmin>
			<ymin>424.77980893273025</ymin>
			<xmax>396.26011756623143</xmax>
			<ymax>147.5432132736367</ymax>
		</bndbox>
	</object>
	<object>
		<name>hand</name>
		<pose>Unspecified</pose>
		<truncated>0</truncated>
		<difficult>0</difficult>
		<bndbox>
			<xmin>354.7006667474939</xmin>
			<ymin>173.68617740736698</ymin>
			<xmax>455.7828544035774</xmax>
			<ymax>147.5432132736367</ymax>
		</bndbox>
	</object>
	<object>
		<name>hand</name>
		<pose>Unspecified</pose>
		<truncated>0</truncated>
		<difficult>0</difficult>
		<bndbox>
			<xmin>396.26011756623143</xmin>
			<ymin>173.68617740736698</ymin>
			<xmax>240.47725068232603</xmax>
			<ymax>147.5432132736367</ymax>
		</bndbox>
	</object>
	<object>
		<name>hand</name>
		<pose>Unspecified</pose>
		<truncated>0</truncated>
		<difficult>0</difficult>
		<bndbox>
			<xmin>396.26011756623143</xmin>
			<ymin>173.68617740736698</ymin>
			<xmax>354.7006667474939</xmax>
			<ymax>623.0241941680266</ymax>
		</bndbox>
	</object>
	<object>
		<name>hand</name>
		<pose>Unspecified</pose>
		<truncated>0</truncated>
		<difficult>0</difficult>
		<bndbox>
			<xmin>354.7006667474939</xmin>
			<ymin>567.0142964584095</ymin>
			<xmax>396.26011756623143</xmax>
			<ymax>147.5432132736367</ymax>
		</bndbox>
	</object>
	<object>
		<name>hand</name>
		<pose>Unspecified</pose>
		<truncated>0</truncated>
		<difficult>0</difficult>
		<bndbox>
			<xmin>491.4283379236199</xmin>
			<ymin>147.5432132736367</ymin>
			<xmax>396.26011756623143</xmax>
			<ymax>147.5432132736367</ymax>
		</bndbox>
	</object>
	<object>
		<name>hand</name>
		<pose>Unspecified</pose>
		<truncated>0</truncated>
		<difficult>0</difficult>
		<bndbox>
			<xmin>412.3436844868374</xmin>
			<ymin>147.5432132736367</ymin>
			<xmax>396.26011756623143</xmax>
			<ymax>147.5432132736367</ymax>
		</bndbox>
	</object>
	<object>
		<name>hand</name>
		<pose>Unspecified</pose>
		<truncated>0</truncated>
		<difficult>0</difficult>
		<bndbox>
			<xmin>420.37628539424674</xmin>
			<ymin>179.191553751453</ymin>
			<xmax>396.26011756623143</xmax>
			<ymax>147.5432132736367</ymax>
		</bndbox>
	</object>
</annotation>
