<annotation>
	<folder>HandDetectionDataset</folder>
	<filename>Poselet_16.jpg</filename>
	<size>
		<width>1024</width>
		<height>768</height>
		<depth>3</depth>
	</size>
	<segmented>0</segmented>
	<object>
		<name>hand</name>
		<pose>Unspecified</pose>
		<truncated>0</truncated>
		<difficult>0</difficult>
		<bndbox>
			<xmin>537.2994405999683</xmin>
			<ymin>356.5293605485639</ymin>
			<xmax>575.5436966549333</xmax>
			<ymax>409.7179512793931</ymax>
		</bndbox>
	</object>
	<object>
		<name>hand</name>
		<pose>Unspecified</pose>
		<truncated>0</truncated>
		<difficult>0</difficult>
		<bndbox>
			<xmin>537.2994405999683</xmin>
			<ymin>403.7575748985698</ymin>
			<xmax>575.5436966549333</xmax>
			<ymax>408.83043581738104</ymax>
		</bndbox>
	</object>
	<object>
		<name>hand</name>
		<pose>Unspecified</pose>
		<truncated>0</truncated>
		<difficult>0</difficult>
		<bndbox>
			<xmin>682.847218765972</xmin>
			<ymin>408.83043581738104</ymin>
			<xmax>575.5436966549333</xmax>
			<ymax>408.83043581738104</ymax>
		</bndbox>
	</object>
	<object>
		<name>hand</name>
		<pose>Unspecified</pose>
		<truncated>0</truncated>
		<difficult>0</difficult>
		<bndbox>
			<xmin>581.0187924641411</xmin>
			<ymin>408.83043581738104</ymin>
			<xmax>575.5436966549333</xmax>
			<ymax>408.83043581738104</ymax>
		</bndbox>
	</object>
	<object>
		<name>hand</name>
		<pose>Unspecified</pose>
		<truncated>0</truncated>
		<difficult>0</difficult>
		<bndbox>
			<xmin>537.2994405999683</xmin>
			<ymin>910.8633581015564</ymin>
			<xmax>575.5436966549333</xmax>
			<ymax>408.83043581738104</ymax>
		</bndbox>
	</object>
	<object>
		<name>hand</name>
		<pose>Unspecified</pose>
		<truncated>0</truncated>
		<difficult>0</difficult>
		<bndbox>
			<xmin>674.5551070620355</xmin>
			<ymin>408.83043581738104</ymin>
			<xmax>575.5436966549333</xmax>
			<ymax>408.83043581738104</ymax>
		</bndbox>
	</object>
</annotation>
