<annotation>
	<folder>HandDetectionDataset</folder>
	<filename>Poselet_151.jpg</filename>
	<size>
		<width>1024</width>
		<height>681</height>
		<depth>3</depth>
	</size>
	<segmented>0</segmented>
	<object>
		<name>hand</name>
		<pose>Unspecified</pose>
		<truncated>0</truncated>
		<difficult>0</difficult>
		<bndbox>
			<xmin>397.2663142450968</xmin>
			<ymin>44.7485789467582</ymin>
			<xmax>451.64545046078547</xmax>
			<ymax>82.8750769672203</ymax>
		</bndbox>
	</object>
	<object>
		<name>hand</name>
		<pose>Unspecified</pose>
		<truncated>0</truncated>
		<difficult>0</difficult>
		<bndbox>
			<xmin>392.82600692107485</xmin>
			<ymin>82.8750769672203</ymin>
			<xmax>445.11435346078304</xmax>
			<ymax>56.67689435894461</ymax>
		</bndbox>
	</object>
	<object>
		<name>hand</name>
		<pose>Unspecified</pose>
		<truncated>0</truncated>
		<difficult>0</difficult>
		<bndbox>
			<xmin>451.64545046078547</xmin>
			<ymin>70.94676155503389</ymin>
			<xmax>397.2663142450968</xmax>
			<ymax>570.5653385920529</ymax>
		</bndbox>
	</object>
	<object>
		<name>hand</name>
		<pose>Unspecified</pose>
		<truncated>0</truncated>
		<difficult>0</difficult>
		<bndbox>
			<xmin>442.64174094087923</xmin>
			<ymin>56.67689435894461</ymin>
			<xmax>451.64545046078547</xmax>
			<ymax>56.67689435894461</ymax>
		</bndbox>
	</object>
</annotation>
