<annotation>
	<folder>HandDetectionDataset</folder>
	<filename>VOC2010_869.jpg</filename>
	<size>
		<width>500</width>
		<height>333</height>
		<depth>3</depth>
	</size>
	<segmented>0</segmented>
	<object>
		<name>hand</name>
		<pose>Unspecified</pose>
		<truncated>0</truncated>
		<difficult>0</difficult>
		<bndbox>
			<xmin>40.38491617048555</xmin>
			<ymin>80.749300017623</ymin>
			<xmax>67.80626030010251</xmax>
			<ymax>101.25428421176764</ymax>
		</bndbox>
	</object>
	<object>
		<name>hand</name>
		<pose>Unspecified</pose>
		<truncated>0</truncated>
		<difficult>0</difficult>
		<bndbox>
			<xmin>44.9533191236319</xmin>
			<ymin>90.15790216816066</ymin>
			<xmax>40.38491617048555</xmax>
			<ymax>240.1426863991833</ymax>
		</bndbox>
	</object>
	<object>
		<name>hand</name>
		<pose>Unspecified</pose>
		<truncated>0</truncated>
		<difficult>0</difficult>
		<bndbox>
			<xmin>44.9533191236319</xmin>
			<ymin>90.15790216816066</ymin>
			<xmax>40.38491617048555</xmax>
			<ymax>316.54648235066395</ymax>
		</bndbox>
	</object>
</annotation>
