<annotation>
	<folder>HandDetectionDataset</folder>
	<filename>VOC2010_518.jpg</filename>
	<size>
		<width>333</width>
		<height>500</height>
		<depth>3</depth>
	</size>
	<segmented>0</segmented>
	<object>
		<name>hand</name>
		<pose>Unspecified</pose>
		<truncated>0</truncated>
		<difficult>0</difficult>
		<bndbox>
			<xmin>264.57342195548074</xmin>
			<ymin>93.24514433240465</ymin>
			<xmax>296.28622716732605</xmax>
			<ymax>117.36315059847094</ymax>
		</bndbox>
	</object>
	<object>
		<name>hand</name>
		<pose>Unspecified</pose>
		<truncated>0</truncated>
		<difficult>0</difficult>
		<bndbox>
			<xmin>296.28622716732605</xmin>
			<ymin>73.45250777521115</ymin>
			<xmax>294.70207692624103</xmax>
			<ymax>115.18803539109767</ymax>
		</bndbox>
	</object>
</annotation>
