<annotation>
	<folder>HandDetectionDataset</folder>
	<filename>VOC2010_1209.jpg</filename>
	<size>
		<width>500</width>
		<height>375</height>
		<depth>3</depth>
	</size>
	<segmented>0</segmented>
	<object>
		<name>hand</name>
		<pose>Unspecified</pose>
		<truncated>0</truncated>
		<difficult>0</difficult>
		<bndbox>
			<xmin>167.15102453662448</xmin>
			<ymin>357.20824655935303</ymin>
			<xmax>212.07119768559772</xmax>
			<ymax>395.97378109041654</ymax>
		</bndbox>
	</object>
	<object>
		<name>hand</name>
		<pose>Unspecified</pose>
		<truncated>0</truncated>
		<difficult>0</difficult>
		<bndbox>
			<xmin>212.07119768559772</xmin>
			<ymin>136.49398075191</ymin>
			<xmax>167.15102453662448</xmax>
			<ymax>359.0054815823945</ymax>
		</bndbox>
	</object>
	<object>
		<name>hand</name>
		<pose>Unspecified</pose>
		<truncated>0</truncated>
		<difficult>0</difficult>
		<bndbox>
			<xmin>212.07119768559772</xmin>
			<ymin>198.433016112083</ymin>
			<xmax>167.15102453662448</xmax>
			<ymax>359.0054815823945</ymax>
		</bndbox>
	</object>
</annotation>
