<annotation>
	<folder>HandDetectionDataset</folder>
	<filename>VOC2007_650.jpg</filename>
	<size>
		<width>500</width>
		<height>352</height>
		<depth>3</depth>
	</size>
	<segmented>0</segmented>
	<object>
		<name>hand</name>
		<pose>Unspecified</pose>
		<truncated>0</truncated>
		<difficult>0</difficult>
		<bndbox>
			<xmin>96.2375552893455</xmin>
			<ymin>258.02379859958285</ymin>
			<xmax>131.9519871943146</xmax>
			<ymax>296.6052336584816</ymax>
		</bndbox>
	</object>
	<object>
		<name>hand</name>
		<pose>Unspecified</pose>
		<truncated>0</truncated>
		<difficult>0</difficult>
		<bndbox>
			<xmin>175.93569177148615</xmin>
			<ymin>296.6052336584816</ymin>
			<xmax>114.69708523353029</xmax>
			<ymax>284.63670182538925</ymax>
		</bndbox>
	</object>
	<object>
		<name>hand</name>
		<pose>Unspecified</pose>
		<truncated>0</truncated>
		<difficult>0</difficult>
		<bndbox>
			<xmin>113.4924572501298</xmin>
			<ymin>296.6052336584816</ymin>
			<xmax>200.03098486120237</xmax>
			<ymax>284.63670182538925</ymax>
		</bndbox>
	</object>
</annotation>
