<annotation>
	<folder>HandDetectionDataset</folder>
	<filename>VOC2010_1118.jpg</filename>
	<size>
		<width>500</width>
		<height>374</height>
		<depth>3</depth>
	</size>
	<segmented>0</segmented>
	<object>
		<name>hand</name>
		<pose>Unspecified</pose>
		<truncated>0</truncated>
		<difficult>0</difficult>
		<bndbox>
			<xmin>259.17063139118216</xmin>
			<ymin>182.77731995941775</ymin>
			<xmax>287.8732282579406</xmax>
			<ymax>214.2871961696145</ymax>
		</bndbox>
	</object>
	<object>
		<name>hand</name>
		<pose>Unspecified</pose>
		<truncated>0</truncated>
		<difficult>0</difficult>
		<bndbox>
			<xmin>260.9191694028781</xmin>
			<ymin>214.2871961696145</ymin>
			<xmax>286.12469024624465</xmax>
			<ymax>245.1852734292823</ymax>
		</bndbox>
	</object>
</annotation>
